README.md
setup.cfg
setup.py
pierpydistributionsdemo/Binomialdistribution.py
pierpydistributionsdemo/Gaussiandistribution.py
pierpydistributionsdemo/Generaldistribution.py
pierpydistributionsdemo/__init__.py
pierpydistributionsdemo.egg-info/PKG-INFO
pierpydistributionsdemo.egg-info/SOURCES.txt
pierpydistributionsdemo.egg-info/dependency_links.txt
pierpydistributionsdemo.egg-info/not-zip-safe
pierpydistributionsdemo.egg-info/top_level.txt